flask_viewsets/__init__.py
flask_viewsets/extension.py
flask_viewsets/grammars/where.lark
flask_viewsets/parsers.py
flask_viewsets/py.typed
flask_viewsets/transformers.py
flask_viewsets/typing.py
flask_viewsets/viewsets.py
flask_viewsets-0.2.6.dist-info/LICENSE.md
flask_viewsets-0.2.6.dist-info/METADATA
flask_viewsets-0.2.6.dist-info/WHEEL
flask_viewsets-0.2.6.dist-info/RECORD
