Metadata-Version: 2.1
Name: Flask-Viewsets
Version: 0.2.6
Summary: Adds Django REST Framework inspired viewsets to Flask.
Home-page: https://github.com/quentinboudinel/Flask-Viewsets
Author: Quentin Boudinel
Author-email: quentin.boudinel@atelier-26.net
Requires-Python: >=3.12,<4.0
Classifier: Programming Language :: Python :: 3
Classifier: Programming Language :: Python :: 3.12
Requires-Dist: flask (>=3.0.3,<4.0.0)
Requires-Dist: lark (>=1.2.2,<2.0.0)
Project-URL: Repository, https://github.com/quentinboudinel/Flask-Viewsets
